well_log_toolkit/__init__.py
well_log_toolkit/exceptions.py
well_log_toolkit/las_file.py
well_log_toolkit/manager.py
well_log_toolkit/operations.py
well_log_toolkit/property.py
well_log_toolkit/regression.py
well_log_toolkit/statistics.py
well_log_toolkit/utils.py
well_log_toolkit/visualization.py
well_log_toolkit/well.py
well_log_toolkit-0.1.149.dist-info/METADATA
well_log_toolkit-0.1.149.dist-info/WHEEL
well_log_toolkit-0.1.149.dist-info/top_level.txt
well_log_toolkit-0.1.149.dist-info/RECORD
