Metadata-Version: 2.4
Name: well-log-toolkit
Version: 0.1.149
Summary: Fast LAS file processing with lazy loading and filtering for well log analysis
Author-email: Kristian dF Kollsgård <kkollsg@gmail.com>
License: MIT
Project-URL: Homepage, https://github.com/kkollsga/well_log_toolkit
Project-URL: Documentation, https://github.com/kkollsga/well_log_toolkit#readme
Project-URL: Repository, https://github.com/kkollsga/well_log_toolkit
Project-URL: Issues, https://github.com/kkollsga/well_log_toolkit/issues
Project-URL: Changelog, https://github.com/kkollsga/well_log_toolkit/releases
Keywords: well-log,las-file,petrophysics,geoscience,oil-and-gas,petroleum-engineering
Classifier: Development Status :: 3 - Alpha
Classifier: Intended Audience :: Science/Research
Classifier: Intended Audience :: Developers
Classifier: License :: OSI Approved :: MIT License
Classifier: Programming Language :: Python :: 3
Classifier: Programming Language :: Python :: 3.9
Classifier: Programming Language :: Python :: 3.10
Classifier: Programming Language :: Python :: 3.11
Classifier: Programming Language :: Python :: 3.12
Classifier: Programming Language :: Python :: 3.13
Classifier: Topic :: Scientific/Engineering
Classifier: Topic :: Software Development :: Libraries :: Python Modules
Classifier: Operating System :: OS Independent
Requires-Python: >=3.9
Requires-Dist: numpy>=1.20.0
Requires-Dist: pandas>=1.3.0
Requires-Dist: scipy>=1.7.0
Requires-Dist: matplotlib>=3.5.0
Provides-Extra: dev
Requires-Dist: pytest>=7.0.0; extra == "dev"
Requires-Dist: pytest-cov>=4.0.0; extra == "dev"
Requires-Dist: black>=23.0.0; extra == "dev"
Requires-Dist: ruff>=0.1.0; extra == "dev"
Requires-Dist: mypy>=1.0.0; extra == "dev"
